gyrus/__init__.py
gyrus/class_factory.py
gyrus/context.py
gyrus/cortex.py
gyrus/cortex_manager.py
gyrus/enums.py
gyrus/exception.py
gyrus/main.py
gyrus/node.py
gyrus/processor.py
gyrus/runtime.py
gyrus/state.py
gyrus/stream.py
gyrus-0.1.9.dist-info/METADATA
gyrus-0.1.9.dist-info/WHEEL
gyrus-0.1.9.dist-info/top_level.txt
gyrus-0.1.9.dist-info/RECORD
