Metadata-Version: 2.4
Name: gyrus
Version: 0.1.9
Summary: A lightweight workflow engine with YAML-based configuration.
Requires-Python: >=3.13
Requires-Dist: pyyaml>=6.0.3
